CHANGES.txt
COPYRIGHT.txt
LICENSE.txt
bootstrap.py
buildout.cfg
setup.py
src/z3c/__init__.py
src/z3c.hashedresource.egg-info/PKG-INFO
src/z3c.hashedresource.egg-info/SOURCES.txt
src/z3c.hashedresource.egg-info/dependency_links.txt
src/z3c.hashedresource.egg-info/namespace_packages.txt
src/z3c.hashedresource.egg-info/not-zip-safe
src/z3c.hashedresource.egg-info/requires.txt
src/z3c.hashedresource.egg-info/top_level.txt
src/z3c/hashedresource/README.txt
src/z3c/hashedresource/__init__.py
src/z3c/hashedresource/configure.zcml
src/z3c/hashedresource/ftesting-devmode.zcml
src/z3c/hashedresource/ftesting.zcml
src/z3c/hashedresource/hash.py
src/z3c/hashedresource/interfaces.py
src/z3c/hashedresource/testing.py
src/z3c/hashedresource/url.py
src/z3c/hashedresource/tests/__init__.py
src/z3c/hashedresource/tests/test_browser.py
src/z3c/hashedresource/tests/test_hash.py
src/z3c/hashedresource/tests/test_url.py
src/z3c/hashedresource/tests/fixture/test.pt
src/z3c/hashedresource/tests/fixture/test.txt