Metadata-Version: 1.0
Name: z3c.hashedresource
Version: 1.1.3
Summary: Provides URLs for resources that change whenever their content changes.
Home-page: http://pypi.python.org/pypi/z3c.hashedresource
Author: Wolfgang Schnerring
Author-email: ws@gocept.com
License: ZPL 2.1
Platform: UNKNOWN
Classifier: Intended Audience :: Developers
Classifier: License :: OSI Approved :: Zope Public License
Classifier: Programming Language :: Python
Classifier: Operating System :: OS Independent
Classifier: Framework :: Zope3
